tagfindutils/__init__.py
tagfindutils/cloudmusic.py
tagfindutils/qqmusic.py
tagfindutils/rawquery.py
tagfindutils/structures.py
tagfindutils/utils.py
MusicTagFindUtils-0.1.2.dist-info/LICENSE
MusicTagFindUtils-0.1.2.dist-info/METADATA
MusicTagFindUtils-0.1.2.dist-info/WHEEL
MusicTagFindUtils-0.1.2.dist-info/top_level.txt
MusicTagFindUtils-0.1.2.dist-info/RECORD
