Metadata-Version: 2.1
Name: MusicTagFindUtils
Version: 0.1.2
Summary: 从音乐平台上获取指定歌曲的标签信息的 Python 库
Author: nukemiko
Maintainer: nukemiko
License: MIT
Keywords: music,audio,netease,163,qqmusic,metadata,tag
Classifier: License :: OSI Approved :: MIT License
Classifier: Operating System :: OS Independent
Classifier: Topic :: Multimedia :: Sound/Audio
Classifier: Programming Language :: Python :: 3.8
Classifier: Programming Language :: Python :: 3.9
Classifier: Programming Language :: Python :: 3.10
Requires-Python: >=3.8
License-File: LICENSE
Requires-Dist: requests
